{"directed": true, "multigraph": false, "graph": {}, 
  "nodes": [{
	 "id": "0", 
	 "label": "{'changeType': 'Add', 'type': 'object', 'className': 'EEnumLiteral', 'attributes': {'id': '_YzfOSt6tEei97MD7GK1RmA', 'name':'Dynamic','value':'3','instance':'Dynamic','literal':'Dynamic','eEnum':'GenDelegationKind'}}" 
},{
	 "id": "1", 
	 "label": "{'changeType': 'Preserve', 'type': 'object', 'className': 'EEnum', 'attributes': {'id': '_YZ3M-t6tEei97MD7GK1RmA', 'name':'GenDelegationKind','defaultValue':'None','ePackage':'genmodel','serializable':'true','eLiterals':['None','Reflective','Virtual','Dynamic']}}" 
}], 
 "links": [{
	 "source": "1", 
	 "target": "0", 
	 "label": "{'changeType': 'Add', 'type': 'reference', 'referenceTypeName': 'eLiterals'}" 
}]}